{
  "inputs": {
    "src/ConditionalSuspense.tsx": {
      "bytes": 449,
      "imports": [
        {
          "path": "react",
          "kind": "import-statement",
          "external": true
        }
      ],
      "format": "esm"
    },
    "src/useIsBrowser.ts": {
      "bytes": 286,
      "imports": [
        {
          "path": "react",
          "kind": "import-statement",
          "external": true
        }
      ],
      "format": "esm"
    },
    "src/useIsIntersecting.ts": {
      "bytes": 645,
      "imports": [
        {
          "path": "react",
          "kind": "import-statement",
          "external": true
        }
      ],
      "format": "esm"
    },
    "src/common/utils.ts": {
      "bytes": 2688,
      "imports": [
        {
          "path": "react",
          "kind": "import-statement",
          "external": true
        }
      ],
      "format": "esm"
    },
    "src/useCombinedRefs.ts": {
      "bytes": 892,
      "imports": [
        {
          "path": "react",
          "kind": "import-statement",
          "external": true
        }
      ],
      "format": "esm"
    },
    "src/useObjectPropEffect.ts": {
      "bytes": 1850,
      "imports": [
        {
          "path": "react",
          "kind": "import-statement",
          "external": true
        }
      ],
      "format": "esm"
    },
    "src/env.ts": {
      "bytes": 245,
      "imports": [],
      "format": "esm"
    },
    "src/end-screen.css": {
      "bytes": 3261,
      "imports": []
    },
    "src/playlist-end-screen.tsx": {
      "bytes": 2955,
      "imports": [
        {
          "path": "react",
          "kind": "import-statement",
          "external": true
        },
        {
          "path": "./mux-news-player",
          "kind": "import-statement",
          "external": true
        },
        {
          "path": "src/end-screen.css",
          "kind": "import-statement",
          "original": "./end-screen.css"
        }
      ],
      "format": "esm"
    },
    "../../node_modules/ce-la-react/dist/ce-la-react.js": {
      "bytes": 4676,
      "imports": [],
      "format": "esm"
    },
    "../../node_modules/media-chrome/dist/constants.js": {
      "bytes": 5737,
      "imports": [],
      "format": "esm"
    },
    "../../node_modules/media-chrome/dist/utils/utils.js": {
      "bytes": 2438,
      "imports": [],
      "format": "esm"
    },
    "../../node_modules/media-chrome/dist/utils/time.js": {
      "bytes": 2674,
      "imports": [
        {
          "path": "../../node_modules/media-chrome/dist/utils/utils.js",
          "kind": "import-statement",
          "original": "./utils.js"
        }
      ],
      "format": "esm"
    },
    "../../node_modules/media-chrome/dist/lang/en.js": {
      "bytes": 2710,
      "imports": [],
      "format": "esm"
    },
    "../../node_modules/media-chrome/dist/utils/i18n.js": {
      "bytes": 764,
      "imports": [
        {
          "path": "../../node_modules/media-chrome/dist/lang/en.js",
          "kind": "import-statement",
          "original": "../lang/en.js"
        }
      ],
      "format": "esm"
    },
    "../../node_modules/media-chrome/dist/utils/server-safe-globals.js": {
      "bytes": 1940,
      "imports": [],
      "format": "esm"
    },
    "../../node_modules/media-chrome/dist/utils/resize-observer.js": {
      "bytes": 848,
      "imports": [
        {
          "path": "../../node_modules/media-chrome/dist/utils/server-safe-globals.js",
          "kind": "import-statement",
          "original": "./server-safe-globals.js"
        }
      ],
      "format": "esm"
    },
    "../../node_modules/media-chrome/dist/utils/element-utils.js": {
      "bytes": 6321,
      "imports": [
        {
          "path": "../../node_modules/media-chrome/dist/constants.js",
          "kind": "import-statement",
          "original": "../constants.js"
        }
      ],
      "format": "esm"
    },
    "../../node_modules/media-chrome/dist/media-gesture-receiver.js": {
      "bytes": 6482,
      "imports": [
        {
          "path": "../../node_modules/media-chrome/dist/constants.js",
          "kind": "import-statement",
          "original": "./constants.js"
        },
        {
          "path": "../../node_modules/media-chrome/dist/utils/element-utils.js",
          "kind": "import-statement",
          "original": "./utils/element-utils.js"
        },
        {
          "path": "../../node_modules/media-chrome/dist/utils/server-safe-globals.js",
          "kind": "import-statement",
          "original": "./utils/server-safe-globals.js"
        }
      ],
      "format": "esm"
    },
    "../../node_modules/media-chrome/dist/media-container.js": {
      "bytes": 19765,
      "imports": [
        {
          "path": "../../node_modules/media-chrome/dist/utils/server-safe-globals.js",
          "kind": "import-statement",
          "original": "./utils/server-safe-globals.js"
        },
        {
          "path": "../../node_modules/media-chrome/dist/constants.js",
          "kind": "import-statement",
          "original": "./constants.js"
        },
        {
          "path": "../../node_modules/media-chrome/dist/utils/resize-observer.js",
          "kind": "import-statement",
          "original": "./utils/resize-observer.js"
        },
        {
          "path": "../../node_modules/media-chrome/dist/media-gesture-receiver.js",
          "kind": "import-statement",
          "original": "./media-gesture-receiver.js"
        },
        {
          "path": "../../node_modules/media-chrome/dist/utils/i18n.js",
          "kind": "import-statement",
          "original": "./utils/i18n.js"
        },
        {
          "path": "../../node_modules/media-chrome/dist/utils/element-utils.js",
          "kind": "import-statement",
          "original": "./utils/element-utils.js"
        }
      ],
      "format": "esm"
    },
    "../../node_modules/media-chrome/dist/utils/attribute-token-list.js": {
      "bytes": 3452,
      "imports": [],
      "format": "esm"
    },
    "../../node_modules/media-chrome/dist/utils/captions.js": {
      "bytes": 2938,
      "imports": [
        {
          "path": "../../node_modules/media-chrome/dist/constants.js",
          "kind": "import-statement",
          "original": "../constants.js"
        }
      ],
      "format": "esm"
    },
    "../../node_modules/media-chrome/dist/utils/fullscreen-api.js": {
      "bytes": 3822,
      "imports": [
        {
          "path": "../../node_modules/media-chrome/dist/constants.js",
          "kind": "import-statement",
          "original": "../constants.js"
        },
        {
          "path": "../../node_modules/media-chrome/dist/utils/element-utils.js",
          "kind": "import-statement",
          "original": "./element-utils.js"
        },
        {
          "path": "../../node_modules/media-chrome/dist/utils/server-safe-globals.js",
          "kind": "import-statement",
          "original": "./server-safe-globals.js"
        }
      ],
      "format": "esm"
    },
    "../../node_modules/media-chrome/dist/utils/platform-tests.js": {
      "bytes": 2097,
      "imports": [
        {
          "path": "../../node_modules/media-chrome/dist/utils/server-safe-globals.js",
          "kind": "import-statement",
          "original": "./server-safe-globals.js"
        },
        {
          "path": "../../node_modules/media-chrome/dist/utils/utils.js",
          "kind": "import-statement",
          "original": "./utils.js"
        },
        {
          "path": "../../node_modules/media-chrome/dist/utils/fullscreen-api.js",
          "kind": "import-statement",
          "original": "./fullscreen-api.js"
        }
      ],
      "format": "esm"
    },
    "../../node_modules/media-chrome/dist/media-store/util.js": {
      "bytes": 3412,
      "imports": [
        {
          "path": "../../node_modules/media-chrome/dist/constants.js",
          "kind": "import-statement",
          "original": "../constants.js"
        },
        {
          "path": "../../node_modules/media-chrome/dist/utils/captions.js",
          "kind": "import-statement",
          "original": "../utils/captions.js"
        }
      ],
      "format": "esm"
    },
    "../../node_modules/media-chrome/dist/media-store/state-mediator.js": {
      "bytes": 28939,
      "imports": [
        {
          "path": "../../node_modules/media-chrome/dist/utils/server-safe-globals.js",
          "kind": "import-statement",
          "original": "../utils/server-safe-globals.js"
        },
        {
          "path": "../../node_modules/media-chrome/dist/constants.js",
          "kind": "import-statement",
          "original": "../constants.js"
        },
        {
          "path": "../../node_modules/media-chrome/dist/utils/element-utils.js",
          "kind": "import-statement",
          "original": "../utils/element-utils.js"
        },
        {
          "path": "../../node_modules/media-chrome/dist/utils/fullscreen-api.js",
          "kind": "import-statement",
          "original": "../utils/fullscreen-api.js"
        },
        {
          "path": "../../node_modules/media-chrome/dist/utils/platform-tests.js",
          "kind": "import-statement",
          "original": "../utils/platform-tests.js"
        },
        {
          "path": "../../node_modules/media-chrome/dist/media-store/util.js",
          "kind": "import-statement",
          "original": "./util.js"
        },
        {
          "path": "../../node_modules/media-chrome/dist/utils/captions.js",
          "kind": "import-statement",
          "original": "../utils/captions.js"
        },
        {
          "path": "../../node_modules/media-chrome/dist/utils/utils.js",
          "kind": "import-statement",
          "original": "../utils/utils.js"
        }
      ],
      "format": "esm"
    },
    "../../node_modules/media-chrome/dist/media-store/request-map.js": {
      "bytes": 8515,
      "imports": [
        {
          "path": "../../node_modules/media-chrome/dist/utils/server-safe-globals.js",
          "kind": "import-statement",
          "original": "../utils/server-safe-globals.js"
        },
        {
          "path": "../../node_modules/media-chrome/dist/constants.js",
          "kind": "import-statement",
          "original": "../constants.js"
        },
        {
          "path": "../../node_modules/media-chrome/dist/utils/captions.js",
          "kind": "import-statement",
          "original": "../utils/captions.js"
        },
        {
          "path": "../../node_modules/media-chrome/dist/media-store/util.js",
          "kind": "import-statement",
          "original": "./util.js"
        }
      ],
      "format": "esm"
    },
    "../../node_modules/media-chrome/dist/media-store/media-store.js": {
      "bytes": 12326,
      "imports": [
        {
          "path": "../../node_modules/media-chrome/dist/media-store/state-mediator.js",
          "kind": "import-statement",
          "original": "./state-mediator.js"
        },
        {
          "path": "../../node_modules/media-chrome/dist/media-store/util.js",
          "kind": "import-statement",
          "original": "./util.js"
        },
        {
          "path": "../../node_modules/media-chrome/dist/media-store/request-map.js",
          "kind": "import-statement",
          "original": "./request-map.js"
        }
      ],
      "format": "esm"
    },
    "../../node_modules/media-chrome/dist/media-controller.js": {
      "bytes": 28341,
      "imports": [
        {
          "path": "../../node_modules/media-chrome/dist/media-container.js",
          "kind": "import-statement",
          "original": "./media-container.js"
        },
        {
          "path": "../../node_modules/media-chrome/dist/utils/server-safe-globals.js",
          "kind": "import-statement",
          "original": "./utils/server-safe-globals.js"
        },
        {
          "path": "../../node_modules/media-chrome/dist/utils/attribute-token-list.js",
          "kind": "import-statement",
          "original": "./utils/attribute-token-list.js"
        },
        {
          "path": "../../node_modules/media-chrome/dist/utils/utils.js",
          "kind": "import-statement",
          "original": "./utils/utils.js"
        },
        {
          "path": "../../node_modules/media-chrome/dist/utils/captions.js",
          "kind": "import-statement",
          "original": "./utils/captions.js"
        },
        {
          "path": "../../node_modules/media-chrome/dist/constants.js",
          "kind": "import-statement",
          "original": "./constants.js"
        },
        {
          "path": "../../node_modules/media-chrome/dist/utils/element-utils.js",
          "kind": "import-statement",
          "original": "./utils/element-utils.js"
        },
        {
          "path": "../../node_modules/media-chrome/dist/media-store/media-store.js",
          "kind": "import-statement",
          "original": "./media-store/media-store.js"
        },
        {
          "path": "../../node_modules/media-chrome/dist/utils/i18n.js",
          "kind": "import-statement",
          "original": "./utils/i18n.js"
        }
      ],
      "format": "esm"
    },
    "../../node_modules/media-chrome/dist/media-chrome-button.js": {
      "bytes": 11042,
      "imports": [
        {
          "path": "../../node_modules/media-chrome/dist/constants.js",
          "kind": "import-statement",
          "original": "./constants.js"
        },
        {
          "path": "../../node_modules/media-chrome/dist/utils/element-utils.js",
          "kind": "import-statement",
          "original": "./utils/element-utils.js"
        },
        {
          "path": "../../node_modules/media-chrome/dist/utils/server-safe-globals.js",
          "kind": "import-statement",
          "original": "./utils/server-safe-globals.js"
        }
      ],
      "format": "esm"
    },
    "../../node_modules/media-chrome/dist/media-airplay-button.js": {
      "bytes": 3421,
      "imports": [
        {
          "path": "../../node_modules/media-chrome/dist/media-chrome-button.js",
          "kind": "import-statement",
          "original": "./media-chrome-button.js"
        },
        {
          "path": "../../node_modules/media-chrome/dist/utils/server-safe-globals.js",
          "kind": "import-statement",
          "original": "./utils/server-safe-globals.js"
        },
        {
          "path": "../../node_modules/media-chrome/dist/constants.js",
          "kind": "import-statement",
          "original": "./constants.js"
        },
        {
          "path": "../../node_modules/media-chrome/dist/utils/i18n.js",
          "kind": "import-statement",
          "original": "./utils/i18n.js"
        },
        {
          "path": "../../node_modules/media-chrome/dist/utils/element-utils.js",
          "kind": "import-statement",
          "original": "./utils/element-utils.js"
        }
      ],
      "format": "esm"
    },
    "../../node_modules/media-chrome/dist/media-captions-button.js": {
      "bytes": 6143,
      "imports": [
        {
          "path": "../../node_modules/media-chrome/dist/media-chrome-button.js",
          "kind": "import-statement",
          "original": "./media-chrome-button.js"
        },
        {
          "path": "../../node_modules/media-chrome/dist/utils/server-safe-globals.js",
          "kind": "import-statement",
          "original": "./utils/server-safe-globals.js"
        },
        {
          "path": "../../node_modules/media-chrome/dist/constants.js",
          "kind": "import-statement",
          "original": "./constants.js"
        },
        {
          "path": "../../node_modules/media-chrome/dist/utils/captions.js",
          "kind": "import-statement",
          "original": "./utils/captions.js"
        },
        {
          "path": "../../node_modules/media-chrome/dist/utils/i18n.js",
          "kind": "import-statement",
          "original": "./utils/i18n.js"
        }
      ],
      "format": "esm"
    },
    "../../node_modules/media-chrome/dist/media-cast-button.js": {
      "bytes": 4293,
      "imports": [
        {
          "path": "../../node_modules/media-chrome/dist/media-chrome-button.js",
          "kind": "import-statement",
          "original": "./media-chrome-button.js"
        },
        {
          "path": "../../node_modules/media-chrome/dist/utils/server-safe-globals.js",
          "kind": "import-statement",
          "original": "./utils/server-safe-globals.js"
        },
        {
          "path": "../../node_modules/media-chrome/dist/constants.js",
          "kind": "import-statement",
          "original": "./constants.js"
        },
        {
          "path": "../../node_modules/media-chrome/dist/utils/i18n.js",
          "kind": "import-statement",
          "original": "./utils/i18n.js"
        },
        {
          "path": "../../node_modules/media-chrome/dist/utils/element-utils.js",
          "kind": "import-statement",
          "original": "./utils/element-utils.js"
        }
      ],
      "format": "esm"
    },
    "../../node_modules/media-chrome/dist/media-chrome-dialog.js": {
      "bytes": 8251,
      "imports": [
        {
          "path": "../../node_modules/media-chrome/dist/utils/server-safe-globals.js",
          "kind": "import-statement",
          "original": "./utils/server-safe-globals.js"
        },
        {
          "path": "../../node_modules/media-chrome/dist/utils/element-utils.js",
          "kind": "import-statement",
          "original": "./utils/element-utils.js"
        }
      ],
      "format": "esm"
    },
    "../../node_modules/media-chrome/dist/media-chrome-range.js": {
      "bytes": 20798,
      "imports": [
        {
          "path": "../../node_modules/media-chrome/dist/constants.js",
          "kind": "import-statement",
          "original": "./constants.js"
        },
        {
          "path": "../../node_modules/media-chrome/dist/utils/server-safe-globals.js",
          "kind": "import-statement",
          "original": "./utils/server-safe-globals.js"
        },
        {
          "path": "../../node_modules/media-chrome/dist/utils/element-utils.js",
          "kind": "import-statement",
          "original": "./utils/element-utils.js"
        },
        {
          "path": "../../node_modules/media-chrome/dist/utils/resize-observer.js",
          "kind": "import-statement",
          "original": "./utils/resize-observer.js"
        }
      ],
      "format": "esm"
    },
    "../../node_modules/media-chrome/dist/media-control-bar.js": {
      "bytes": 3611,
      "imports": [
        {
          "path": "../../node_modules/media-chrome/dist/constants.js",
          "kind": "import-statement",
          "original": "./constants.js"
        },
        {
          "path": "../../node_modules/media-chrome/dist/utils/server-safe-globals.js",
          "kind": "import-statement",
          "original": "./utils/server-safe-globals.js"
        }
      ],
      "format": "esm"
    },
    "../../node_modules/media-chrome/dist/media-text-display.js": {
      "bytes": 4436,
      "imports": [
        {
          "path": "../../node_modules/media-chrome/dist/constants.js",
          "kind": "import-statement",
          "original": "./constants.js"
        },
        {
          "path": "../../node_modules/media-chrome/dist/utils/element-utils.js",
          "kind": "import-statement",
          "original": "./utils/element-utils.js"
        },
        {
          "path": "../../node_modules/media-chrome/dist/utils/server-safe-globals.js",
          "kind": "import-statement",
          "original": "./utils/server-safe-globals.js"
        }
      ],
      "format": "esm"
    },
    "../../node_modules/media-chrome/dist/media-duration-display.js": {
      "bytes": 2199,
      "imports": [
        {
          "path": "../../node_modules/media-chrome/dist/media-text-display.js",
          "kind": "import-statement",
          "original": "./media-text-display.js"
        },
        {
          "path": "../../node_modules/media-chrome/dist/utils/server-safe-globals.js",
          "kind": "import-statement",
          "original": "./utils/server-safe-globals.js"
        },
        {
          "path": "../../node_modules/media-chrome/dist/utils/time.js",
          "kind": "import-statement",
          "original": "./utils/time.js"
        },
        {
          "path": "../../node_modules/media-chrome/dist/constants.js",
          "kind": "import-statement",
          "original": "./constants.js"
        },
        {
          "path": "../../node_modules/media-chrome/dist/utils/element-utils.js",
          "kind": "import-statement",
          "original": "./utils/element-utils.js"
        }
      ],
      "format": "esm"
    },
    "../../node_modules/media-chrome/dist/labels/labels.js": {
      "bytes": 909,
      "imports": [
        {
          "path": "../../node_modules/media-chrome/dist/utils/i18n.js",
          "kind": "import-statement",
          "original": "../utils/i18n.js"
        }
      ],
      "format": "esm"
    },
    "../../node_modules/media-chrome/dist/media-error-dialog.js": {
      "bytes": 3880,
      "imports": [
        {
          "path": "../../node_modules/media-chrome/dist/utils/server-safe-globals.js",
          "kind": "import-statement",
          "original": "./utils/server-safe-globals.js"
        },
        {
          "path": "../../node_modules/media-chrome/dist/constants.js",
          "kind": "import-statement",
          "original": "./constants.js"
        },
        {
          "path": "../../node_modules/media-chrome/dist/labels/labels.js",
          "kind": "import-statement",
          "original": "./labels/labels.js"
        },
        {
          "path": "../../node_modules/media-chrome/dist/media-chrome-dialog.js",
          "kind": "import-statement",
          "original": "./media-chrome-dialog.js"
        },
        {
          "path": "../../node_modules/media-chrome/dist/utils/element-utils.js",
          "kind": "import-statement",
          "original": "./utils/element-utils.js"
        }
      ],
      "format": "esm"
    },
    "../../node_modules/media-chrome/dist/media-fullscreen-button.js": {
      "bytes": 3704,
      "imports": [
        {
          "path": "../../node_modules/media-chrome/dist/media-chrome-button.js",
          "kind": "import-statement",
          "original": "./media-chrome-button.js"
        },
        {
          "path": "../../node_modules/media-chrome/dist/utils/server-safe-globals.js",
          "kind": "import-statement",
          "original": "./utils/server-safe-globals.js"
        },
        {
          "path": "../../node_modules/media-chrome/dist/constants.js",
          "kind": "import-statement",
          "original": "./constants.js"
        },
        {
          "path": "../../node_modules/media-chrome/dist/utils/i18n.js",
          "kind": "import-statement",
          "original": "./utils/i18n.js"
        },
        {
          "path": "../../node_modules/media-chrome/dist/utils/element-utils.js",
          "kind": "import-statement",
          "original": "./utils/element-utils.js"
        }
      ],
      "format": "esm"
    },
    "../../node_modules/media-chrome/dist/media-live-button.js": {
      "bytes": 3716,
      "imports": [
        {
          "path": "../../node_modules/media-chrome/dist/media-chrome-button.js",
          "kind": "import-statement",
          "original": "./media-chrome-button.js"
        },
        {
          "path": "../../node_modules/media-chrome/dist/utils/server-safe-globals.js",
          "kind": "import-statement",
          "original": "./utils/server-safe-globals.js"
        },
        {
          "path": "../../node_modules/media-chrome/dist/constants.js",
          "kind": "import-statement",
          "original": "./constants.js"
        },
        {
          "path": "../../node_modules/media-chrome/dist/utils/element-utils.js",
          "kind": "import-statement",
          "original": "./utils/element-utils.js"
        },
        {
          "path": "../../node_modules/media-chrome/dist/utils/i18n.js",
          "kind": "import-statement",
          "original": "./utils/i18n.js"
        }
      ],
      "format": "esm"
    },
    "../../node_modules/media-chrome/dist/media-loading-indicator.js": {
      "bytes": 6903,
      "imports": [
        {
          "path": "../../node_modules/media-chrome/dist/constants.js",
          "kind": "import-statement",
          "original": "./constants.js"
        },
        {
          "path": "../../node_modules/media-chrome/dist/utils/server-safe-globals.js",
          "kind": "import-statement",
          "original": "./utils/server-safe-globals.js"
        },
        {
          "path": "../../node_modules/media-chrome/dist/utils/element-utils.js",
          "kind": "import-statement",
          "original": "./utils/element-utils.js"
        },
        {
          "path": "../../node_modules/media-chrome/dist/utils/i18n.js",
          "kind": "import-statement",
          "original": "./utils/i18n.js"
        }
      ],
      "format": "esm"
    },
    "../../node_modules/media-chrome/dist/media-mute-button.js": {
      "bytes": 3809,
      "imports": [
        {
          "path": "../../node_modules/media-chrome/dist/media-chrome-button.js",
          "kind": "import-statement",
          "original": "./media-chrome-button.js"
        },
        {
          "path": "../../node_modules/media-chrome/dist/utils/server-safe-globals.js",
          "kind": "import-statement",
          "original": "./utils/server-safe-globals.js"
        },
        {
          "path": "../../node_modules/media-chrome/dist/constants.js",
          "kind": "import-statement",
          "original": "./constants.js"
        },
        {
          "path": "../../node_modules/media-chrome/dist/utils/i18n.js",
          "kind": "import-statement",
          "original": "./utils/i18n.js"
        },
        {
          "path": "../../node_modules/media-chrome/dist/utils/element-utils.js",
          "kind": "import-statement",
          "original": "./utils/element-utils.js"
        }
      ],
      "format": "esm"
    },
    "../../node_modules/media-chrome/dist/media-pip-button.js": {
      "bytes": 3296,
      "imports": [
        {
          "path": "../../node_modules/media-chrome/dist/media-chrome-button.js",
          "kind": "import-statement",
          "original": "./media-chrome-button.js"
        },
        {
          "path": "../../node_modules/media-chrome/dist/utils/server-safe-globals.js",
          "kind": "import-statement",
          "original": "./utils/server-safe-globals.js"
        },
        {
          "path": "../../node_modules/media-chrome/dist/constants.js",
          "kind": "import-statement",
          "original": "./constants.js"
        },
        {
          "path": "../../node_modules/media-chrome/dist/utils/i18n.js",
          "kind": "import-statement",
          "original": "./utils/i18n.js"
        },
        {
          "path": "../../node_modules/media-chrome/dist/utils/element-utils.js",
          "kind": "import-statement",
          "original": "./utils/element-utils.js"
        }
      ],
      "format": "esm"
    },
    "../../node_modules/media-chrome/dist/media-playback-rate-button.js": {
      "bytes": 4041,
      "imports": [
        {
          "path": "../../node_modules/media-chrome/dist/media-chrome-button.js",
          "kind": "import-statement",
          "original": "./media-chrome-button.js"
        },
        {
          "path": "../../node_modules/media-chrome/dist/utils/server-safe-globals.js",
          "kind": "import-statement",
          "original": "./utils/server-safe-globals.js"
        },
        {
          "path": "../../node_modules/media-chrome/dist/constants.js",
          "kind": "import-statement",
          "original": "./constants.js"
        },
        {
          "path": "../../node_modules/media-chrome/dist/utils/attribute-token-list.js",
          "kind": "import-statement",
          "original": "./utils/attribute-token-list.js"
        },
        {
          "path": "../../node_modules/media-chrome/dist/utils/element-utils.js",
          "kind": "import-statement",
          "original": "./utils/element-utils.js"
        },
        {
          "path": "../../node_modules/media-chrome/dist/utils/i18n.js",
          "kind": "import-statement",
          "original": "./utils/i18n.js"
        }
      ],
      "format": "esm"
    },
    "../../node_modules/media-chrome/dist/media-play-button.js": {
      "bytes": 2738,
      "imports": [
        {
          "path": "../../node_modules/media-chrome/dist/media-chrome-button.js",
          "kind": "import-statement",
          "original": "./media-chrome-button.js"
        },
        {
          "path": "../../node_modules/media-chrome/dist/utils/server-safe-globals.js",
          "kind": "import-statement",
          "original": "./utils/server-safe-globals.js"
        },
        {
          "path": "../../node_modules/media-chrome/dist/constants.js",
          "kind": "import-statement",
          "original": "./constants.js"
        },
        {
          "path": "../../node_modules/media-chrome/dist/utils/i18n.js",
          "kind": "import-statement",
          "original": "./utils/i18n.js"
        },
        {
          "path": "../../node_modules/media-chrome/dist/utils/element-utils.js",
          "kind": "import-statement",
          "original": "./utils/element-utils.js"
        }
      ],
      "format": "esm"
    },
    "../../node_modules/media-chrome/dist/media-poster-image.js": {
      "bytes": 2650,
      "imports": [
        {
          "path": "../../node_modules/media-chrome/dist/utils/server-safe-globals.js",
          "kind": "import-statement",
          "original": "./utils/server-safe-globals.js"
        },
        {
          "path": "../../node_modules/media-chrome/dist/utils/element-utils.js",
          "kind": "import-statement",
          "original": "./utils/element-utils.js"
        }
      ],
      "format": "esm"
    },
    "../../node_modules/media-chrome/dist/media-preview-chapter-display.js": {
      "bytes": 2406,
      "imports": [
        {
          "path": "../../node_modules/media-chrome/dist/media-text-display.js",
          "kind": "import-statement",
          "original": "./media-text-display.js"
        },
        {
          "path": "../../node_modules/media-chrome/dist/utils/server-safe-globals.js",
          "kind": "import-statement",
          "original": "./utils/server-safe-globals.js"
        },
        {
          "path": "../../node_modules/media-chrome/dist/constants.js",
          "kind": "import-statement",
          "original": "./constants.js"
        },
        {
          "path": "../../node_modules/media-chrome/dist/utils/element-utils.js",
          "kind": "import-statement",
          "original": "./utils/element-utils.js"
        }
      ],
      "format": "esm"
    },
    "../../node_modules/media-chrome/dist/media-preview-thumbnail.js": {
      "bytes": 6126,
      "imports": [
        {
          "path": "../../node_modules/media-chrome/dist/utils/server-safe-globals.js",
          "kind": "import-statement",
          "original": "./utils/server-safe-globals.js"
        },
        {
          "path": "../../node_modules/media-chrome/dist/constants.js",
          "kind": "import-statement",
          "original": "./constants.js"
        },
        {
          "path": "../../node_modules/media-chrome/dist/utils/element-utils.js",
          "kind": "import-statement",
          "original": "./utils/element-utils.js"
        }
      ],
      "format": "esm"
    },
    "../../node_modules/media-chrome/dist/media-preview-time-display.js": {
      "bytes": 2228,
      "imports": [
        {
          "path": "../../node_modules/media-chrome/dist/media-text-display.js",
          "kind": "import-statement",
          "original": "./media-text-display.js"
        },
        {
          "path": "../../node_modules/media-chrome/dist/utils/server-safe-globals.js",
          "kind": "import-statement",
          "original": "./utils/server-safe-globals.js"
        },
        {
          "path": "../../node_modules/media-chrome/dist/utils/time.js",
          "kind": "import-statement",
          "original": "./utils/time.js"
        },
        {
          "path": "../../node_modules/media-chrome/dist/constants.js",
          "kind": "import-statement",
          "original": "./constants.js"
        },
        {
          "path": "../../node_modules/media-chrome/dist/utils/element-utils.js",
          "kind": "import-statement",
          "original": "./utils/element-utils.js"
        }
      ],
      "format": "esm"
    },
    "../../node_modules/media-chrome/dist/media-seek-backward-button.js": {
      "bytes": 3156,
      "imports": [
        {
          "path": "../../node_modules/media-chrome/dist/media-chrome-button.js",
          "kind": "import-statement",
          "original": "./media-chrome-button.js"
        },
        {
          "path": "../../node_modules/media-chrome/dist/utils/server-safe-globals.js",
          "kind": "import-statement",
          "original": "./utils/server-safe-globals.js"
        },
        {
          "path": "../../node_modules/media-chrome/dist/constants.js",
          "kind": "import-statement",
          "original": "./constants.js"
        },
        {
          "path": "../../node_modules/media-chrome/dist/utils/element-utils.js",
          "kind": "import-statement",
          "original": "./utils/element-utils.js"
        },
        {
          "path": "../../node_modules/media-chrome/dist/utils/i18n.js",
          "kind": "import-statement",
          "original": "./utils/i18n.js"
        },
        {
          "path": "../../node_modules/media-chrome/dist/utils/element-utils.js",
          "kind": "import-statement",
          "original": "./utils/element-utils.js"
        }
      ],
      "format": "esm"
    },
    "../../node_modules/media-chrome/dist/media-seek-forward-button.js": {
      "bytes": 3135,
      "imports": [
        {
          "path": "../../node_modules/media-chrome/dist/media-chrome-button.js",
          "kind": "import-statement",
          "original": "./media-chrome-button.js"
        },
        {
          "path": "../../node_modules/media-chrome/dist/utils/server-safe-globals.js",
          "kind": "import-statement",
          "original": "./utils/server-safe-globals.js"
        },
        {
          "path": "../../node_modules/media-chrome/dist/constants.js",
          "kind": "import-statement",
          "original": "./constants.js"
        },
        {
          "path": "../../node_modules/media-chrome/dist/utils/element-utils.js",
          "kind": "import-statement",
          "original": "./utils/element-utils.js"
        },
        {
          "path": "../../node_modules/media-chrome/dist/utils/i18n.js",
          "kind": "import-statement",
          "original": "./utils/i18n.js"
        },
        {
          "path": "../../node_modules/media-chrome/dist/utils/element-utils.js",
          "kind": "import-statement",
          "original": "./utils/element-utils.js"
        }
      ],
      "format": "esm"
    },
    "../../node_modules/media-chrome/dist/media-time-display.js": {
      "bytes": 7749,
      "imports": [
        {
          "path": "../../node_modules/media-chrome/dist/media-text-display.js",
          "kind": "import-statement",
          "original": "./media-text-display.js"
        },
        {
          "path": "../../node_modules/media-chrome/dist/utils/element-utils.js",
          "kind": "import-statement",
          "original": "./utils/element-utils.js"
        },
        {
          "path": "../../node_modules/media-chrome/dist/utils/server-safe-globals.js",
          "kind": "import-statement",
          "original": "./utils/server-safe-globals.js"
        },
        {
          "path": "../../node_modules/media-chrome/dist/utils/time.js",
          "kind": "import-statement",
          "original": "./utils/time.js"
        },
        {
          "path": "../../node_modules/media-chrome/dist/constants.js",
          "kind": "import-statement",
          "original": "./constants.js"
        },
        {
          "path": "../../node_modules/media-chrome/dist/utils/i18n.js",
          "kind": "import-statement",
          "original": "./utils/i18n.js"
        }
      ],
      "format": "esm"
    },
    "../../node_modules/media-chrome/dist/utils/range-animation.js": {
      "bytes": 3973,
      "imports": [],
      "format": "esm"
    },
    "../../node_modules/media-chrome/dist/media-time-range.js": {
      "bytes": 28692,
      "imports": [
        {
          "path": "../../node_modules/media-chrome/dist/utils/server-safe-globals.js",
          "kind": "import-statement",
          "original": "./utils/server-safe-globals.js"
        },
        {
          "path": "../../node_modules/media-chrome/dist/media-chrome-range.js",
          "kind": "import-statement",
          "original": "./media-chrome-range.js"
        },
        {
          "path": "../../node_modules/media-chrome/dist/media-preview-thumbnail.js",
          "kind": "import-statement",
          "original": "./media-preview-thumbnail.js"
        },
        {
          "path": "../../node_modules/media-chrome/dist/media-preview-time-display.js",
          "kind": "import-statement",
          "original": "./media-preview-time-display.js"
        },
        {
          "path": "../../node_modules/media-chrome/dist/media-preview-chapter-display.js",
          "kind": "import-statement",
          "original": "./media-preview-chapter-display.js"
        },
        {
          "path": "../../node_modules/media-chrome/dist/constants.js",
          "kind": "import-statement",
          "original": "./constants.js"
        },
        {
          "path": "../../node_modules/media-chrome/dist/utils/utils.js",
          "kind": "import-statement",
          "original": "./utils/utils.js"
        },
        {
          "path": "../../node_modules/media-chrome/dist/utils/time.js",
          "kind": "import-statement",
          "original": "./utils/time.js"
        },
        {
          "path": "../../node_modules/media-chrome/dist/utils/element-utils.js",
          "kind": "import-statement",
          "original": "./utils/element-utils.js"
        },
        {
          "path": "../../node_modules/media-chrome/dist/utils/range-animation.js",
          "kind": "import-statement",
          "original": "./utils/range-animation.js"
        },
        {
          "path": "../../node_modules/media-chrome/dist/utils/element-utils.js",
          "kind": "import-statement",
          "original": "./utils/element-utils.js"
        },
        {
          "path": "../../node_modules/media-chrome/dist/utils/i18n.js",
          "kind": "import-statement",
          "original": "./utils/i18n.js"
        }
      ],
      "format": "esm"
    },
    "../../node_modules/media-chrome/dist/media-tooltip.js": {
      "bytes": 7651,
      "imports": [
        {
          "path": "../../node_modules/media-chrome/dist/utils/element-utils.js",
          "kind": "import-statement",
          "original": "./utils/element-utils.js"
        },
        {
          "path": "../../node_modules/media-chrome/dist/utils/server-safe-globals.js",
          "kind": "import-statement",
          "original": "./utils/server-safe-globals.js"
        }
      ],
      "format": "esm"
    },
    "../../node_modules/media-chrome/dist/media-volume-range.js": {
      "bytes": 2698,
      "imports": [
        {
          "path": "../../node_modules/media-chrome/dist/utils/server-safe-globals.js",
          "kind": "import-statement",
          "original": "./utils/server-safe-globals.js"
        },
        {
          "path": "../../node_modules/media-chrome/dist/media-chrome-range.js",
          "kind": "import-statement",
          "original": "./media-chrome-range.js"
        },
        {
          "path": "../../node_modules/media-chrome/dist/constants.js",
          "kind": "import-statement",
          "original": "./constants.js"
        },
        {
          "path": "../../node_modules/media-chrome/dist/utils/i18n.js",
          "kind": "import-statement",
          "original": "./utils/i18n.js"
        },
        {
          "path": "../../node_modules/media-chrome/dist/utils/element-utils.js",
          "kind": "import-statement",
          "original": "./utils/element-utils.js"
        }
      ],
      "format": "esm"
    },
    "../../node_modules/media-chrome/dist/index.js": {
      "bytes": 2605,
      "imports": [
        {
          "path": "../../node_modules/media-chrome/dist/constants.js",
          "kind": "import-statement",
          "original": "./constants.js"
        },
        {
          "path": "../../node_modules/media-chrome/dist/utils/time.js",
          "kind": "import-statement",
          "original": "./utils/time.js"
        },
        {
          "path": "../../node_modules/media-chrome/dist/utils/i18n.js",
          "kind": "import-statement",
          "original": "./utils/i18n.js"
        },
        {
          "path": "../../node_modules/media-chrome/dist/media-controller.js",
          "kind": "import-statement",
          "original": "./media-controller.js"
        },
        {
          "path": "../../node_modules/media-chrome/dist/media-airplay-button.js",
          "kind": "import-statement",
          "original": "./media-airplay-button.js"
        },
        {
          "path": "../../node_modules/media-chrome/dist/media-captions-button.js",
          "kind": "import-statement",
          "original": "./media-captions-button.js"
        },
        {
          "path": "../../node_modules/media-chrome/dist/media-cast-button.js",
          "kind": "import-statement",
          "original": "./media-cast-button.js"
        },
        {
          "path": "../../node_modules/media-chrome/dist/media-chrome-button.js",
          "kind": "import-statement",
          "original": "./media-chrome-button.js"
        },
        {
          "path": "../../node_modules/media-chrome/dist/media-chrome-dialog.js",
          "kind": "import-statement",
          "original": "./media-chrome-dialog.js"
        },
        {
          "path": "../../node_modules/media-chrome/dist/media-chrome-range.js",
          "kind": "import-statement",
          "original": "./media-chrome-range.js"
        },
        {
          "path": "../../node_modules/media-chrome/dist/media-control-bar.js",
          "kind": "import-statement",
          "original": "./media-control-bar.js"
        },
        {
          "path": "../../node_modules/media-chrome/dist/media-duration-display.js",
          "kind": "import-statement",
          "original": "./media-duration-display.js"
        },
        {
          "path": "../../node_modules/media-chrome/dist/media-error-dialog.js",
          "kind": "import-statement",
          "original": "./media-error-dialog.js"
        },
        {
          "path": "../../node_modules/media-chrome/dist/media-fullscreen-button.js",
          "kind": "import-statement",
          "original": "./media-fullscreen-button.js"
        },
        {
          "path": "../../node_modules/media-chrome/dist/media-gesture-receiver.js",
          "kind": "import-statement",
          "original": "./media-gesture-receiver.js"
        },
        {
          "path": "../../node_modules/media-chrome/dist/media-live-button.js",
          "kind": "import-statement",
          "original": "./media-live-button.js"
        },
        {
          "path": "../../node_modules/media-chrome/dist/media-loading-indicator.js",
          "kind": "import-statement",
          "original": "./media-loading-indicator.js"
        },
        {
          "path": "../../node_modules/media-chrome/dist/media-mute-button.js",
          "kind": "import-statement",
          "original": "./media-mute-button.js"
        },
        {
          "path": "../../node_modules/media-chrome/dist/media-pip-button.js",
          "kind": "import-statement",
          "original": "./media-pip-button.js"
        },
        {
          "path": "../../node_modules/media-chrome/dist/media-playback-rate-button.js",
          "kind": "import-statement",
          "original": "./media-playback-rate-button.js"
        },
        {
          "path": "../../node_modules/media-chrome/dist/media-play-button.js",
          "kind": "import-statement",
          "original": "./media-play-button.js"
        },
        {
          "path": "../../node_modules/media-chrome/dist/media-poster-image.js",
          "kind": "import-statement",
          "original": "./media-poster-image.js"
        },
        {
          "path": "../../node_modules/media-chrome/dist/media-preview-chapter-display.js",
          "kind": "import-statement",
          "original": "./media-preview-chapter-display.js"
        },
        {
          "path": "../../node_modules/media-chrome/dist/media-preview-thumbnail.js",
          "kind": "import-statement",
          "original": "./media-preview-thumbnail.js"
        },
        {
          "path": "../../node_modules/media-chrome/dist/media-preview-time-display.js",
          "kind": "import-statement",
          "original": "./media-preview-time-display.js"
        },
        {
          "path": "../../node_modules/media-chrome/dist/media-seek-backward-button.js",
          "kind": "import-statement",
          "original": "./media-seek-backward-button.js"
        },
        {
          "path": "../../node_modules/media-chrome/dist/media-seek-forward-button.js",
          "kind": "import-statement",
          "original": "./media-seek-forward-button.js"
        },
        {
          "path": "../../node_modules/media-chrome/dist/media-time-display.js",
          "kind": "import-statement",
          "original": "./media-time-display.js"
        },
        {
          "path": "../../node_modules/media-chrome/dist/media-time-range.js",
          "kind": "import-statement",
          "original": "./media-time-range.js"
        },
        {
          "path": "../../node_modules/media-chrome/dist/media-tooltip.js",
          "kind": "import-statement",
          "original": "./media-tooltip.js"
        },
        {
          "path": "../../node_modules/media-chrome/dist/media-volume-range.js",
          "kind": "import-statement",
          "original": "./media-volume-range.js"
        },
        {
          "path": "../../node_modules/media-chrome/dist/media-container.js",
          "kind": "import-statement",
          "original": "./media-container.js"
        },
        {
          "path": "../../node_modules/media-chrome/dist/media-text-display.js",
          "kind": "import-statement",
          "original": "./media-text-display.js"
        }
      ],
      "format": "esm"
    },
    "../../node_modules/media-chrome/dist/react/index.js": {
      "bytes": 4648,
      "imports": [
        {
          "path": "react",
          "kind": "import-statement",
          "external": true
        },
        {
          "path": "../../node_modules/ce-la-react/dist/ce-la-react.js",
          "kind": "import-statement",
          "original": "ce-la-react"
        },
        {
          "path": "../../node_modules/media-chrome/dist/index.js",
          "kind": "import-statement",
          "original": "../index.js"
        }
      ],
      "format": "esm"
    },
    "../../node_modules/media-chrome/dist/utils/anchor-utils.js": {
      "bytes": 2164,
      "imports": [],
      "format": "esm"
    },
    "../../node_modules/media-chrome/dist/utils/events.js": {
      "bytes": 523,
      "imports": [],
      "format": "esm"
    },
    "../../node_modules/media-chrome/dist/menu/media-chrome-menu.js": {
      "bytes": 28686,
      "imports": [
        {
          "path": "../../node_modules/media-chrome/dist/constants.js",
          "kind": "import-statement",
          "original": "../constants.js"
        },
        {
          "path": "../../node_modules/media-chrome/dist/utils/server-safe-globals.js",
          "kind": "import-statement",
          "original": "../utils/server-safe-globals.js"
        },
        {
          "path": "../../node_modules/media-chrome/dist/utils/anchor-utils.js",
          "kind": "import-statement",
          "original": "../utils/anchor-utils.js"
        },
        {
          "path": "../../node_modules/media-chrome/dist/utils/resize-observer.js",
          "kind": "import-statement",
          "original": "../utils/resize-observer.js"
        },
        {
          "path": "../../node_modules/media-chrome/dist/utils/events.js",
          "kind": "import-statement",
          "original": "../utils/events.js"
        },
        {
          "path": "../../node_modules/media-chrome/dist/utils/element-utils.js",
          "kind": "import-statement",
          "original": "../utils/element-utils.js"
        }
      ],
      "format": "esm"
    },
    "../../node_modules/media-chrome/dist/menu/media-chrome-menu-item.js": {
      "bytes": 14264,
      "imports": [
        {
          "path": "../../node_modules/media-chrome/dist/utils/server-safe-globals.js",
          "kind": "import-statement",
          "original": "../utils/server-safe-globals.js"
        },
        {
          "path": "../../node_modules/media-chrome/dist/utils/events.js",
          "kind": "import-statement",
          "original": "../utils/events.js"
        },
        {
          "path": "../../node_modules/media-chrome/dist/utils/element-utils.js",
          "kind": "import-statement",
          "original": "../utils/element-utils.js"
        }
      ],
      "format": "esm"
    },
    "../../node_modules/media-chrome/dist/menu/media-settings-menu.js": {
      "bytes": 1860,
      "imports": [
        {
          "path": "../../node_modules/media-chrome/dist/utils/server-safe-globals.js",
          "kind": "import-statement",
          "original": "../utils/server-safe-globals.js"
        },
        {
          "path": "../../node_modules/media-chrome/dist/menu/media-chrome-menu.js",
          "kind": "import-statement",
          "original": "./media-chrome-menu.js"
        },
        {
          "path": "../../node_modules/media-chrome/dist/utils/element-utils.js",
          "kind": "import-statement",
          "original": "../utils/element-utils.js"
        }
      ],
      "format": "esm"
    },
    "../../node_modules/media-chrome/dist/menu/media-settings-menu-item.js": {
      "bytes": 1229,
      "imports": [
        {
          "path": "../../node_modules/media-chrome/dist/utils/server-safe-globals.js",
          "kind": "import-statement",
          "original": "../utils/server-safe-globals.js"
        },
        {
          "path": "../../node_modules/media-chrome/dist/menu/media-chrome-menu-item.js",
          "kind": "import-statement",
          "original": "./media-chrome-menu-item.js"
        }
      ],
      "format": "esm"
    },
    "../../node_modules/media-chrome/dist/menu/media-chrome-menu-button.js": {
      "bytes": 1434,
      "imports": [
        {
          "path": "../../node_modules/media-chrome/dist/media-chrome-button.js",
          "kind": "import-statement",
          "original": "../media-chrome-button.js"
        },
        {
          "path": "../../node_modules/media-chrome/dist/utils/server-safe-globals.js",
          "kind": "import-statement",
          "original": "../utils/server-safe-globals.js"
        },
        {
          "path": "../../node_modules/media-chrome/dist/utils/events.js",
          "kind": "import-statement",
          "original": "../utils/events.js"
        },
        {
          "path": "../../node_modules/media-chrome/dist/utils/element-utils.js",
          "kind": "import-statement",
          "original": "../utils/element-utils.js"
        }
      ],
      "format": "esm"
    },
    "../../node_modules/media-chrome/dist/menu/media-settings-menu-button.js": {
      "bytes": 1672,
      "imports": [
        {
          "path": "../../node_modules/media-chrome/dist/menu/media-chrome-menu-button.js",
          "kind": "import-statement",
          "original": "./media-chrome-menu-button.js"
        },
        {
          "path": "../../node_modules/media-chrome/dist/utils/server-safe-globals.js",
          "kind": "import-statement",
          "original": "../utils/server-safe-globals.js"
        },
        {
          "path": "../../node_modules/media-chrome/dist/utils/element-utils.js",
          "kind": "import-statement",
          "original": "../utils/element-utils.js"
        },
        {
          "path": "../../node_modules/media-chrome/dist/utils/i18n.js",
          "kind": "import-statement",
          "original": "../utils/i18n.js"
        }
      ],
      "format": "esm"
    },
    "../../node_modules/media-chrome/dist/menu/media-audio-track-menu.js": {
      "bytes": 4739,
      "imports": [
        {
          "path": "../../node_modules/media-chrome/dist/utils/server-safe-globals.js",
          "kind": "import-statement",
          "original": "../utils/server-safe-globals.js"
        },
        {
          "path": "../../node_modules/media-chrome/dist/constants.js",
          "kind": "import-statement",
          "original": "../constants.js"
        },
        {
          "path": "../../node_modules/media-chrome/dist/utils/utils.js",
          "kind": "import-statement",
          "original": "../utils/utils.js"
        },
        {
          "path": "../../node_modules/media-chrome/dist/menu/media-chrome-menu.js",
          "kind": "import-statement",
          "original": "./media-chrome-menu.js"
        },
        {
          "path": "../../node_modules/media-chrome/dist/utils/element-utils.js",
          "kind": "import-statement",
          "original": "../utils/element-utils.js"
        }
      ],
      "format": "esm"
    },
    "../../node_modules/media-chrome/dist/menu/media-audio-track-menu-button.js": {
      "bytes": 2493,
      "imports": [
        {
          "path": "../../node_modules/media-chrome/dist/constants.js",
          "kind": "import-statement",
          "original": "../constants.js"
        },
        {
          "path": "../../node_modules/media-chrome/dist/menu/media-chrome-menu-button.js",
          "kind": "import-statement",
          "original": "./media-chrome-menu-button.js"
        },
        {
          "path": "../../node_modules/media-chrome/dist/utils/server-safe-globals.js",
          "kind": "import-statement",
          "original": "../utils/server-safe-globals.js"
        },
        {
          "path": "../../node_modules/media-chrome/dist/utils/element-utils.js",
          "kind": "import-statement",
          "original": "../utils/element-utils.js"
        },
        {
          "path": "../../node_modules/media-chrome/dist/utils/i18n.js",
          "kind": "import-statement",
          "original": "../utils/i18n.js"
        }
      ],
      "format": "esm"
    },
    "../../node_modules/media-chrome/dist/menu/media-captions-menu.js": {
      "bytes": 7393,
      "imports": [
        {
          "path": "../../node_modules/media-chrome/dist/utils/server-safe-globals.js",
          "kind": "import-statement",
          "original": "../utils/server-safe-globals.js"
        },
        {
          "path": "../../node_modules/media-chrome/dist/constants.js",
          "kind": "import-statement",
          "original": "../constants.js"
        },
        {
          "path": "../../node_modules/media-chrome/dist/utils/element-utils.js",
          "kind": "import-statement",
          "original": "../utils/element-utils.js"
        },
        {
          "path": "../../node_modules/media-chrome/dist/menu/media-chrome-menu.js",
          "kind": "import-statement",
          "original": "./media-chrome-menu.js"
        },
        {
          "path": "../../node_modules/media-chrome/dist/utils/captions.js",
          "kind": "import-statement",
          "original": "../utils/captions.js"
        }
      ],
      "format": "esm"
    },
    "../../node_modules/media-chrome/dist/menu/media-captions-menu-button.js": {
      "bytes": 6769,
      "imports": [
        {
          "path": "../../node_modules/media-chrome/dist/utils/server-safe-globals.js",
          "kind": "import-statement",
          "original": "../utils/server-safe-globals.js"
        },
        {
          "path": "../../node_modules/media-chrome/dist/constants.js",
          "kind": "import-statement",
          "original": "../constants.js"
        },
        {
          "path": "../../node_modules/media-chrome/dist/menu/media-chrome-menu-button.js",
          "kind": "import-statement",
          "original": "./media-chrome-menu-button.js"
        },
        {
          "path": "../../node_modules/media-chrome/dist/utils/element-utils.js",
          "kind": "import-statement",
          "original": "../utils/element-utils.js"
        },
        {
          "path": "../../node_modules/media-chrome/dist/utils/captions.js",
          "kind": "import-statement",
          "original": "../utils/captions.js"
        },
        {
          "path": "../../node_modules/media-chrome/dist/utils/i18n.js",
          "kind": "import-statement",
          "original": "../utils/i18n.js"
        }
      ],
      "format": "esm"
    },
    "../../node_modules/media-chrome/dist/menu/media-playback-rate-menu.js": {
      "bytes": 4435,
      "imports": [
        {
          "path": "../../node_modules/media-chrome/dist/utils/server-safe-globals.js",
          "kind": "import-statement",
          "original": "../utils/server-safe-globals.js"
        },
        {
          "path": "../../node_modules/media-chrome/dist/constants.js",
          "kind": "import-statement",
          "original": "../constants.js"
        },
        {
          "path": "../../node_modules/media-chrome/dist/utils/attribute-token-list.js",
          "kind": "import-statement",
          "original": "../utils/attribute-token-list.js"
        },
        {
          "path": "../../node_modules/media-chrome/dist/utils/element-utils.js",
          "kind": "import-statement",
          "original": "../utils/element-utils.js"
        },
        {
          "path": "../../node_modules/media-chrome/dist/media-playback-rate-button.js",
          "kind": "import-statement",
          "original": "../media-playback-rate-button.js"
        },
        {
          "path": "../../node_modules/media-chrome/dist/menu/media-chrome-menu.js",
          "kind": "import-statement",
          "original": "./media-chrome-menu.js"
        }
      ],
      "format": "esm"
    },
    "../../node_modules/media-chrome/dist/menu/media-playback-rate-menu-button.js": {
      "bytes": 3957,
      "imports": [
        {
          "path": "../../node_modules/media-chrome/dist/utils/server-safe-globals.js",
          "kind": "import-statement",
          "original": "../utils/server-safe-globals.js"
        },
        {
          "path": "../../node_modules/media-chrome/dist/constants.js",
          "kind": "import-statement",
          "original": "../constants.js"
        },
        {
          "path": "../../node_modules/media-chrome/dist/menu/media-chrome-menu-button.js",
          "kind": "import-statement",
          "original": "./media-chrome-menu-button.js"
        },
        {
          "path": "../../node_modules/media-chrome/dist/utils/attribute-token-list.js",
          "kind": "import-statement",
          "original": "../utils/attribute-token-list.js"
        },
        {
          "path": "../../node_modules/media-chrome/dist/utils/element-utils.js",
          "kind": "import-statement",
          "original": "../utils/element-utils.js"
        },
        {
          "path": "../../node_modules/media-chrome/dist/utils/i18n.js",
          "kind": "import-statement",
          "original": "../utils/i18n.js"
        }
      ],
      "format": "esm"
    },
    "../../node_modules/media-chrome/dist/menu/media-rendition-menu.js": {
      "bytes": 5975,
      "imports": [
        {
          "path": "../../node_modules/media-chrome/dist/utils/server-safe-globals.js",
          "kind": "import-statement",
          "original": "../utils/server-safe-globals.js"
        },
        {
          "path": "../../node_modules/media-chrome/dist/constants.js",
          "kind": "import-statement",
          "original": "../constants.js"
        },
        {
          "path": "../../node_modules/media-chrome/dist/utils/element-utils.js",
          "kind": "import-statement",
          "original": "../utils/element-utils.js"
        },
        {
          "path": "../../node_modules/media-chrome/dist/utils/utils.js",
          "kind": "import-statement",
          "original": "../utils/utils.js"
        },
        {
          "path": "../../node_modules/media-chrome/dist/menu/media-chrome-menu.js",
          "kind": "import-statement",
          "original": "./media-chrome-menu.js"
        }
      ],
      "format": "esm"
    },
    "../../node_modules/media-chrome/dist/menu/media-rendition-menu-button.js": {
      "bytes": 2417,
      "imports": [
        {
          "path": "../../node_modules/media-chrome/dist/constants.js",
          "kind": "import-statement",
          "original": "../constants.js"
        },
        {
          "path": "../../node_modules/media-chrome/dist/menu/media-chrome-menu-button.js",
          "kind": "import-statement",
          "original": "./media-chrome-menu-button.js"
        },
        {
          "path": "../../node_modules/media-chrome/dist/utils/server-safe-globals.js",
          "kind": "import-statement",
          "original": "../utils/server-safe-globals.js"
        },
        {
          "path": "../../node_modules/media-chrome/dist/utils/element-utils.js",
          "kind": "import-statement",
          "original": "../utils/element-utils.js"
        },
        {
          "path": "../../node_modules/media-chrome/dist/utils/i18n.js",
          "kind": "import-statement",
          "original": "../utils/i18n.js"
        }
      ],
      "format": "esm"
    },
    "../../node_modules/media-chrome/dist/menu/index.js": {
      "bytes": 1341,
      "imports": [
        {
          "path": "../../node_modules/media-chrome/dist/menu/media-chrome-menu.js",
          "kind": "import-statement",
          "original": "./media-chrome-menu.js"
        },
        {
          "path": "../../node_modules/media-chrome/dist/menu/media-chrome-menu-item.js",
          "kind": "import-statement",
          "original": "./media-chrome-menu-item.js"
        },
        {
          "path": "../../node_modules/media-chrome/dist/menu/media-settings-menu.js",
          "kind": "import-statement",
          "original": "./media-settings-menu.js"
        },
        {
          "path": "../../node_modules/media-chrome/dist/menu/media-settings-menu-item.js",
          "kind": "import-statement",
          "original": "./media-settings-menu-item.js"
        },
        {
          "path": "../../node_modules/media-chrome/dist/menu/media-settings-menu-button.js",
          "kind": "import-statement",
          "original": "./media-settings-menu-button.js"
        },
        {
          "path": "../../node_modules/media-chrome/dist/menu/media-audio-track-menu.js",
          "kind": "import-statement",
          "original": "./media-audio-track-menu.js"
        },
        {
          "path": "../../node_modules/media-chrome/dist/menu/media-audio-track-menu-button.js",
          "kind": "import-statement",
          "original": "./media-audio-track-menu-button.js"
        },
        {
          "path": "../../node_modules/media-chrome/dist/menu/media-captions-menu.js",
          "kind": "import-statement",
          "original": "./media-captions-menu.js"
        },
        {
          "path": "../../node_modules/media-chrome/dist/menu/media-captions-menu-button.js",
          "kind": "import-statement",
          "original": "./media-captions-menu-button.js"
        },
        {
          "path": "../../node_modules/media-chrome/dist/menu/media-playback-rate-menu.js",
          "kind": "import-statement",
          "original": "./media-playback-rate-menu.js"
        },
        {
          "path": "../../node_modules/media-chrome/dist/menu/media-playback-rate-menu-button.js",
          "kind": "import-statement",
          "original": "./media-playback-rate-menu-button.js"
        },
        {
          "path": "../../node_modules/media-chrome/dist/menu/media-rendition-menu.js",
          "kind": "import-statement",
          "original": "./media-rendition-menu.js"
        },
        {
          "path": "../../node_modules/media-chrome/dist/menu/media-rendition-menu-button.js",
          "kind": "import-statement",
          "original": "./media-rendition-menu-button.js"
        },
        {
          "path": "../../node_modules/media-chrome/dist/menu/media-chrome-menu-button.js",
          "kind": "import-statement",
          "original": "./media-chrome-menu-button.js"
        }
      ],
      "format": "esm"
    },
    "../../node_modules/media-chrome/dist/react/menu/index.js": {
      "bytes": 2375,
      "imports": [
        {
          "path": "react",
          "kind": "import-statement",
          "external": true
        },
        {
          "path": "../../node_modules/ce-la-react/dist/ce-la-react.js",
          "kind": "import-statement",
          "original": "ce-la-react"
        },
        {
          "path": "../../node_modules/media-chrome/dist/menu/index.js",
          "kind": "import-statement",
          "original": "../../menu/index.js"
        }
      ],
      "format": "esm"
    },
    "src/themes/news-theme.tsx": {
      "bytes": 20990,
      "imports": [
        {
          "path": "../../node_modules/media-chrome/dist/react/index.js",
          "kind": "import-statement",
          "original": "media-chrome/react"
        },
        {
          "path": "../../node_modules/media-chrome/dist/react/menu/index.js",
          "kind": "import-statement",
          "original": "media-chrome/react/menu"
        },
        {
          "path": "react",
          "kind": "import-statement",
          "external": true
        }
      ],
      "format": "esm"
    },
    "src/mux-news-player.tsx": {
      "bytes": 3196,
      "imports": [
        {
          "path": "react",
          "kind": "import-statement",
          "external": true
        },
        {
          "path": "src/playlist-end-screen.tsx",
          "kind": "import-statement",
          "original": "./playlist-end-screen"
        },
        {
          "path": "@mux/mux-video-ads",
          "kind": "import-statement",
          "external": true
        },
        {
          "path": "@mux/mux-player-react",
          "kind": "import-statement",
          "external": true
        },
        {
          "path": "src/themes/news-theme.tsx",
          "kind": "import-statement",
          "original": "./themes/news-theme"
        }
      ],
      "format": "esm"
    },
    "src/index.tsx": {
      "bytes": 10860,
      "imports": [
        {
          "path": "react",
          "kind": "import-statement",
          "external": true
        },
        {
          "path": "@mux/playback-core",
          "kind": "import-statement",
          "external": true
        },
        {
          "path": "@mux/mux-player",
          "kind": "import-statement",
          "external": true
        },
        {
          "path": "src/common/utils.ts",
          "kind": "import-statement",
          "original": "./common/utils"
        },
        {
          "path": "react",
          "kind": "import-statement",
          "external": true
        },
        {
          "path": "src/useCombinedRefs.ts",
          "kind": "import-statement",
          "original": "./useCombinedRefs"
        },
        {
          "path": "src/useObjectPropEffect.ts",
          "kind": "import-statement",
          "original": "./useObjectPropEffect"
        },
        {
          "path": "src/env.ts",
          "kind": "import-statement",
          "original": "./env"
        },
        {
          "path": "src/mux-news-player.tsx",
          "kind": "import-statement",
          "original": "./mux-news-player"
        },
        {
          "path": "src/playlist-end-screen.tsx",
          "kind": "import-statement",
          "original": "./playlist-end-screen"
        }
      ],
      "format": "esm"
    },
    "src/lazy.tsx": {
      "bytes": 4460,
      "imports": [
        {
          "path": "react",
          "kind": "import-statement",
          "external": true
        },
        {
          "path": "src/ConditionalSuspense.tsx",
          "kind": "import-statement",
          "original": "./ConditionalSuspense"
        },
        {
          "path": "src/useIsBrowser.ts",
          "kind": "import-statement",
          "original": "./useIsBrowser"
        },
        {
          "path": "src/useIsIntersecting.ts",
          "kind": "import-statement",
          "original": "./useIsIntersecting"
        },
        {
          "path": "src/index.tsx",
          "kind": "dynamic-import",
          "original": "./index"
        }
      ],
      "format": "esm"
    }
  },
  "outputs": {
    "dist/lazy.mjs.map": {
      "imports": [],
      "exports": [],
      "inputs": {},
      "bytes": 8941
    },
    "dist/lazy.mjs": {
      "imports": [
        {
          "path": "react",
          "kind": "import-statement",
          "external": true
        },
        {
          "path": "react",
          "kind": "import-statement",
          "external": true
        },
        {
          "path": "react",
          "kind": "import-statement",
          "external": true
        },
        {
          "path": "react",
          "kind": "import-statement",
          "external": true
        },
        {
          "path": "dist/-4XCR56OH.mjs",
          "kind": "dynamic-import"
        }
      ],
      "exports": [
        "default"
      ],
      "entryPoint": "src/lazy.tsx",
      "inputs": {
        "src/lazy.tsx": {
          "bytesInOutput": 1687
        },
        "src/ConditionalSuspense.tsx": {
          "bytesInOutput": 166
        },
        "src/useIsBrowser.ts": {
          "bytesInOutput": 134
        },
        "src/useIsIntersecting.ts": {
          "bytesInOutput": 274
        }
      },
      "bytes": 2330
    },
    "dist/-4XCR56OH.mjs.map": {
      "imports": [],
      "exports": [],
      "inputs": {},
      "bytes": 729228
    },
    "dist/-4XCR56OH.mjs": {
      "imports": [
        {
          "path": "react",
          "kind": "import-statement",
          "external": true
        },
        {
          "path": "@mux/playback-core",
          "kind": "import-statement",
          "external": true
        },
        {
          "path": "@mux/mux-player",
          "kind": "import-statement",
          "external": true
        },
        {
          "path": "react",
          "kind": "import-statement",
          "external": true
        },
        {
          "path": "react",
          "kind": "import-statement",
          "external": true
        },
        {
          "path": "react",
          "kind": "import-statement",
          "external": true
        },
        {
          "path": "react",
          "kind": "import-statement",
          "external": true
        },
        {
          "path": "react",
          "kind": "import-statement",
          "external": true
        },
        {
          "path": "react",
          "kind": "import-statement",
          "external": true
        },
        {
          "path": "@mux/mux-video-ads",
          "kind": "import-statement",
          "external": true
        },
        {
          "path": "@mux/mux-player-react",
          "kind": "import-statement",
          "external": true
        },
        {
          "path": "react",
          "kind": "import-statement",
          "external": true
        },
        {
          "path": "react",
          "kind": "import-statement",
          "external": true
        },
        {
          "path": "react",
          "kind": "import-statement",
          "external": true
        }
      ],
      "exports": [
        "MaxResolution",
        "MediaError",
        "MinResolution",
        "MuxNewsPlayer",
        "PlaylistEndScreen",
        "RenditionOrder",
        "default",
        "generatePlayerInitTime",
        "playerSoftwareName",
        "playerSoftwareVersion"
      ],
      "entryPoint": "src/index.tsx",
      "inputs": {
        "src/index.tsx": {
          "bytesInOutput": 2264
        },
        "src/common/utils.ts": {
          "bytesInOutput": 623
        },
        "src/useCombinedRefs.ts": {
          "bytesInOutput": 178
        },
        "src/useObjectPropEffect.ts": {
          "bytesInOutput": 605
        },
        "src/env.ts": {
          "bytesInOutput": 72
        },
        "src/mux-news-player.tsx": {
          "bytesInOutput": 1149
        },
        "src/playlist-end-screen.tsx": {
          "bytesInOutput": 1817
        },
        "src/end-screen.css": {
          "bytesInOutput": 3271
        },
        "../../node_modules/media-chrome/dist/react/index.js": {
          "bytesInOutput": 1908
        },
        "../../node_modules/ce-la-react/dist/ce-la-react.js": {
          "bytesInOutput": 2125
        },
        "../../node_modules/media-chrome/dist/constants.js": {
          "bytesInOutput": 3905
        },
        "../../node_modules/media-chrome/dist/utils/utils.js": {
          "bytesInOutput": 719
        },
        "../../node_modules/media-chrome/dist/utils/time.js": {
          "bytesInOutput": 1120
        },
        "../../node_modules/media-chrome/dist/lang/en.js": {
          "bytesInOutput": 2455
        },
        "../../node_modules/media-chrome/dist/utils/i18n.js": {
          "bytesInOutput": 266
        },
        "../../node_modules/media-chrome/dist/utils/server-safe-globals.js": {
          "bytesInOutput": 1098
        },
        "../../node_modules/media-chrome/dist/utils/resize-observer.js": {
          "bytesInOutput": 260
        },
        "../../node_modules/media-chrome/dist/utils/element-utils.js": {
          "bytesInOutput": 2563
        },
        "../../node_modules/media-chrome/dist/media-gesture-receiver.js": {
          "bytesInOutput": 3012
        },
        "../../node_modules/media-chrome/dist/media-container.js": {
          "bytesInOutput": 10777
        },
        "../../node_modules/media-chrome/dist/utils/attribute-token-list.js": {
          "bytesInOutput": 1684
        },
        "../../node_modules/media-chrome/dist/utils/captions.js": {
          "bytesInOutput": 946
        },
        "../../node_modules/media-chrome/dist/utils/fullscreen-api.js": {
          "bytesInOutput": 1554
        },
        "../../node_modules/media-chrome/dist/utils/platform-tests.js": {
          "bytesInOutput": 761
        },
        "../../node_modules/media-chrome/dist/media-store/util.js": {
          "bytesInOutput": 1236
        },
        "../../node_modules/media-chrome/dist/media-store/state-mediator.js": {
          "bytesInOutput": 13162
        },
        "../../node_modules/media-chrome/dist/media-store/request-map.js": {
          "bytesInOutput": 3198
        },
        "../../node_modules/media-chrome/dist/media-store/media-store.js": {
          "bytesInOutput": 4035
        },
        "../../node_modules/media-chrome/dist/media-controller.js": {
          "bytesInOutput": 13141
        },
        "../../node_modules/media-chrome/dist/media-chrome-button.js": {
          "bytesInOutput": 6361
        },
        "../../node_modules/media-chrome/dist/media-airplay-button.js": {
          "bytesInOutput": 1964
        },
        "../../node_modules/media-chrome/dist/media-captions-button.js": {
          "bytesInOutput": 4232
        },
        "../../node_modules/media-chrome/dist/media-cast-button.js": {
          "bytesInOutput": 2806
        },
        "../../node_modules/media-chrome/dist/media-chrome-dialog.js": {
          "bytesInOutput": 4644
        },
        "../../node_modules/media-chrome/dist/media-chrome-range.js": {
          "bytesInOutput": 13409
        },
        "../../node_modules/media-chrome/dist/media-control-bar.js": {
          "bytesInOutput": 2012
        },
        "../../node_modules/media-chrome/dist/media-text-display.js": {
          "bytesInOutput": 2567
        },
        "../../node_modules/media-chrome/dist/media-duration-display.js": {
          "bytesInOutput": 923
        },
        "../../node_modules/media-chrome/dist/labels/labels.js": {
          "bytesInOutput": 600
        },
        "../../node_modules/media-chrome/dist/media-error-dialog.js": {
          "bytesInOutput": 2080
        },
        "../../node_modules/media-chrome/dist/media-fullscreen-button.js": {
          "bytesInOutput": 2122
        },
        "../../node_modules/media-chrome/dist/media-live-button.js": {
          "bytesInOutput": 2027
        },
        "../../node_modules/media-chrome/dist/media-loading-indicator.js": {
          "bytesInOutput": 4044
        },
        "../../node_modules/media-chrome/dist/media-mute-button.js": {
          "bytesInOutput": 2495
        },
        "../../node_modules/media-chrome/dist/media-pip-button.js": {
          "bytesInOutput": 1810
        },
        "../../node_modules/media-chrome/dist/media-playback-rate-button.js": {
          "bytesInOutput": 1822
        },
        "../../node_modules/media-chrome/dist/media-play-button.js": {
          "bytesInOutput": 1525
        },
        "../../node_modules/media-chrome/dist/media-poster-image.js": {
          "bytesInOutput": 1624
        },
        "../../node_modules/media-chrome/dist/media-preview-chapter-display.js": {
          "bytesInOutput": 1056
        },
        "../../node_modules/media-chrome/dist/media-preview-thumbnail.js": {
          "bytesInOutput": 3049
        },
        "../../node_modules/media-chrome/dist/media-preview-time-display.js": {
          "bytesInOutput": 973
        },
        "../../node_modules/media-chrome/dist/media-seek-backward-button.js": {
          "bytesInOutput": 1501
        },
        "../../node_modules/media-chrome/dist/media-seek-forward-button.js": {
          "bytesInOutput": 1488
        },
        "../../node_modules/media-chrome/dist/media-time-display.js": {
          "bytesInOutput": 3604
        },
        "../../node_modules/media-chrome/dist/utils/range-animation.js": {
          "bytesInOutput": 1711
        },
        "../../node_modules/media-chrome/dist/media-time-range.js": {
          "bytesInOutput": 17274
        },
        "../../node_modules/media-chrome/dist/media-tooltip.js": {
          "bytesInOutput": 5667
        },
        "../../node_modules/media-chrome/dist/media-volume-range.js": {
          "bytesInOutput": 1163
        },
        "../../node_modules/media-chrome/dist/react/menu/index.js": {
          "bytesInOutput": 971
        },
        "../../node_modules/media-chrome/dist/utils/anchor-utils.js": {
          "bytesInOutput": 970
        },
        "../../node_modules/media-chrome/dist/utils/events.js": {
          "bytesInOutput": 251
        },
        "../../node_modules/media-chrome/dist/menu/media-chrome-menu.js": {
          "bytesInOutput": 15851
        },
        "../../node_modules/media-chrome/dist/menu/media-chrome-menu-item.js": {
          "bytesInOutput": 8832
        },
        "../../node_modules/media-chrome/dist/menu/media-settings-menu.js": {
          "bytesInOutput": 1171
        },
        "../../node_modules/media-chrome/dist/menu/media-settings-menu-item.js": {
          "bytesInOutput": 713
        },
        "../../node_modules/media-chrome/dist/menu/media-chrome-menu-button.js": {
          "bytesInOutput": 596
        },
        "../../node_modules/media-chrome/dist/menu/media-settings-menu-button.js": {
          "bytesInOutput": 897
        },
        "../../node_modules/media-chrome/dist/menu/media-audio-track-menu.js": {
          "bytesInOutput": 2208
        },
        "../../node_modules/media-chrome/dist/menu/media-audio-track-menu-button.js": {
          "bytesInOutput": 1262
        },
        "../../node_modules/media-chrome/dist/menu/media-captions-menu.js": {
          "bytesInOutput": 3939
        },
        "../../node_modules/media-chrome/dist/menu/media-captions-menu-button.js": {
          "bytesInOutput": 4348
        },
        "../../node_modules/media-chrome/dist/menu/media-playback-rate-menu.js": {
          "bytesInOutput": 1912
        },
        "../../node_modules/media-chrome/dist/menu/media-playback-rate-menu-button.js": {
          "bytesInOutput": 1783
        },
        "../../node_modules/media-chrome/dist/menu/media-rendition-menu.js": {
          "bytesInOutput": 2901
        },
        "../../node_modules/media-chrome/dist/menu/media-rendition-menu-button.js": {
          "bytesInOutput": 1189
        },
        "src/themes/news-theme.tsx": {
          "bytesInOutput": 20872
        }
      },
      "bytes": 247665
    }
  }
}
